MANIFEST.in
README.md
setup.cfg
setup.py
aws_cfn_control.egg-info/PKG-INFO
aws_cfn_control.egg-info/SOURCES.txt
aws_cfn_control.egg-info/dependency_links.txt
aws_cfn_control.egg-info/entry_points.txt
aws_cfn_control.egg-info/not-zip-safe
aws_cfn_control.egg-info/requires.txt
aws_cfn_control.egg-info/top_level.txt
awscfnctl/__init__.py
awscfnctl/asgctl.py
awscfnctl/awscfnctl.py
awscfnctl/build_ami_maps.py
awscfnctl/cfnctl.py
awscfnctl/get_asg_from_stack.py
awscfnctl/get_inst_from_asg.py
awscfnctl/get_priv_dns_asg.py
awscfnctl/getamiinfo.py
awscfnctl/getec2keys.py
awscfnctl/getinstinfo.py
awscfnctl/getnetinfo.py
awscfnctl/getstackinfo.py