Metadata-Version: 2.1
Name: aws-cfn-control
Version: 0.0.16
Summary: Command line launch and management tool for AWS CloudFormation
Home-page: https://github.com/awslabs/aws-cfn-control
Author: Mark Duffield
Author-email: duff@amazon.com
License: Apache License 2.0
Keywords: aws cfn control cloudformation stack
Platform: UNKNOWN
Classifier: Intended Audience :: Developers
Classifier: Natural Language :: English
Classifier: Environment :: Web Environment
Classifier: License :: OSI Approved :: Apache Software License
Classifier: Operating System :: OS Independent
Classifier: Development Status :: 1 - Planning
Classifier: Programming Language :: Python
Classifier: Programming Language :: Python :: 2.7
Classifier: Topic :: Software Development :: Libraries :: Python Modules
Classifier: Topic :: Utilities
